evdev_trigger/__about__.py
evdev_trigger/__init__.py
evdev_trigger/config.py
evdev_trigger/main.py
evdev_trigger/actions/example.py
evdev_trigger/actions/example_complex/__init__.py
evdev_trigger/actions/example_complex/some_file.py
evdev_trigger/core/input_devices.py
evdev_trigger/core/spawners.py
evdev_trigger/core/storage.py
evdev_trigger/models/__init__.py
evdev_trigger/models/action_base.py
evdev_trigger/models/devices.py
evdev_trigger-0.0.2.dist-info/METADATA
evdev_trigger-0.0.2.dist-info/WHEEL
evdev_trigger-0.0.2.dist-info/entry_points.txt
evdev_trigger-0.0.2.dist-info/licenses/LICENSE.txt
evdev_trigger-0.0.2.dist-info/RECORD
