Metadata-Version: 2.3
Name: evdev-trigger
Version: 0.0.2
Summary: Trigger actions based on evdev events from input devices.
Project-URL: Documentation, https://github.com/codekuu/evdev-trigger#readme
Project-URL: Issues, https://github.com/codekuu/evdev-trigger/issues
Project-URL: Source, https://github.com/codekuu/evdev-trigger
Author-email: codekuu <hello-evdev-trigger@inaktiverad.se>
License-Expression: MIT
License-File: LICENSE.txt
Classifier: Development Status :: 4 - Beta
Classifier: Programming Language :: Python
Classifier: Programming Language :: Python :: 3.8
Classifier: Programming Language :: Python :: 3.9
Classifier: Programming Language :: Python :: 3.10
Classifier: Programming Language :: Python :: 3.11
Classifier: Programming Language :: Python :: 3.12
Classifier: Programming Language :: Python :: Implementation :: CPython
Classifier: Programming Language :: Python :: Implementation :: PyPy
Requires-Python: >=3.8
Requires-Dist: evdev==1.7.0
Requires-Dist: pick==2.2.0
Requires-Dist: python-dotenv==1.0.1
Requires-Dist: typer==0.12.3
